mudopy/__init__.py
mudopy-1.5.dist-info/LICENSE.txt
mudopy-1.5.dist-info/METADATA
mudopy-1.5.dist-info/WHEEL
mudopy-1.5.dist-info/top_level.txt
mudopy-1.5.dist-info/RECORD
