Metadata-Version: 2.1
Name: mudopy
Version: 1.5
Summary: Download any song using this library
Home-page: https://github.com/cyborg7898/Geet-Song-Downloader-
Author: Smit Parmar
Author-email: smitparmar3333@gmail.com
License: MIT
Download-URL: https://github.com/Ankit404butfound/awesomepy/archive/1.0.tar.gz
Keywords: get_url,download
Platform: UNKNOWN
Classifier: Development Status :: 3 - Alpha
Classifier: Intended Audience :: Developers
Classifier: Topic :: Software Development :: Build Tools
Classifier: License :: OSI Approved :: MIT License
Classifier: Programming Language :: Python :: 3
Classifier: Programming Language :: Python :: 3.4
Classifier: Programming Language :: Python :: 3.5
Classifier: Programming Language :: Python :: 3.6
Requires-Dist: beautifulsoup4
Requires-Dist: requests
Requires-Dist: selenium
